gping/__init__.py
gping/pinger.py
gping/termsize.py
pinggraph-1.2.dist-info/LICENSE.md
pinggraph-1.2.dist-info/METADATA
pinggraph-1.2.dist-info/WHEEL
pinggraph-1.2.dist-info/entry_points.txt
pinggraph-1.2.dist-info/top_level.txt
pinggraph-1.2.dist-info/RECORD
